sclab/__init__.py
sclab/_io.py
sclab/_methods_registry.py
sclab/_sclab.py
sclab/dataset/__init__.py
sclab/dataset/_dataset.py
sclab/dataset/_exceptions.py
sclab/dataset/plotter/__init__.py
sclab/dataset/plotter/_controls.py
sclab/dataset/plotter/_plotter.py
sclab/dataset/plotter/_utils.py
sclab/dataset/processor/__init__.py
sclab/dataset/processor/_processor.py
sclab/dataset/processor/_results_panel.py
sclab/dataset/processor/step/__init__.py
sclab/dataset/processor/step/_basic_processor_step.py
sclab/dataset/processor/step/_processor_step_base.py
sclab/event/__init__.py
sclab/event/_broker.py
sclab/event/_client.py
sclab/event/_utils.py
sclab/examples/__init__.py
sclab/examples/processor_steps/__init__.py
sclab/examples/processor_steps/_cluster.py
sclab/examples/processor_steps/_differential_expression.py
sclab/examples/processor_steps/_doublet_detection.py
sclab/examples/processor_steps/_gene_expression.py
sclab/examples/processor_steps/_integration.py
sclab/examples/processor_steps/_neighbors.py
sclab/examples/processor_steps/_pca.py
sclab/examples/processor_steps/_preprocess.py
sclab/examples/processor_steps/_qc.py
sclab/examples/processor_steps/_umap.py
sclab/gui/__init__.py
sclab/gui/components/__init__.py
sclab/gui/components/_guided_pseudotime.py
sclab/gui/components/_transfer_metadata.py
sclab/methods/__init__.py
sclab/preprocess/__init__.py
sclab/preprocess/_cca.py
sclab/preprocess/_cca_integrate.py
sclab/preprocess/_filter_obs.py
sclab/preprocess/_harmony.py
sclab/preprocess/_harmony_integrate.py
sclab/preprocess/_normalize_weighted.py
sclab/preprocess/_pca.py
sclab/preprocess/_preprocess.py
sclab/preprocess/_qc.py
sclab/preprocess/_rpca.py
sclab/preprocess/_subset.py
sclab/preprocess/_transfer_metadata.py
sclab/preprocess/_transform.py
sclab/preprocess/_utils.py
sclab/scanpy/__init__.py
sclab/scanpy/_compat.py
sclab/scanpy/_settings.py
sclab/scanpy/logging.py
sclab/scanpy/readwrite.py
sclab/scanpy/plotting/__init__.py
sclab/scanpy/plotting/_rcmod.py
sclab-0.3.4.dist-info/licenses/LICENSE
sclab-0.3.4.dist-info/WHEEL
sclab-0.3.4.dist-info/METADATA
sclab-0.3.4.dist-info/RECORD
