Metadata-Version: 2.4
Name: sclab
Version: 0.3.4
Summary: sclab
Author-email: Argenis Arriojas <ArriojasMaldonado001@umb.edu>
Requires-Python: >=3.10,<3.13
Classifier: License :: OSI Approved :: BSD License
Classifier: Programming Language :: Python :: 3
Classifier: Programming Language :: Python :: 3.10
Classifier: Programming Language :: Python :: 3.11
Classifier: Programming Language :: Python :: 3.12
License-File: LICENSE
Requires-Dist: anndata
Requires-Dist: anywidget
Requires-Dist: ipywidgets
Requires-Dist: itables<2.4
Requires-Dist: matplotlib
Requires-Dist: numpy<2.2
Requires-Dist: pandas
Requires-Dist: plotly<6.0
Requires-Dist: requests
Requires-Dist: ripser>=0.6.12
Requires-Dist: scikit-learn
Requires-Dist: scipy<1.16
Requires-Dist: svgpathtools
Requires-Dist: tqdm
Requires-Dist: jupyterlab>=4.3.6 ; extra == "jupyter"
Requires-Dist: anndata2ri>=1.3 ; extra == "r"
Requires-Dist: rpy2>=3.5 ; extra == "r"
Requires-Dist: scanpy[leiden, skmisc]>=1.10 ; extra == "scanpy"
Requires-Dist: pytest>=8.3.4 ; extra == "test"
Project-URL: Bug Tracker, https://github.com/umbibio/sclab/issues
Project-URL: Changelog, https://github.com/umbibio/sclab/blob/main/CHANGELOG.md
Project-URL: Documentation, https://github.com/umbibio/sclab/docs
Project-URL: Homepage, https://github.com/umbibio/sclab
Project-URL: Repository, https://github.com/umbibio/sclab.git
Provides-Extra: jupyter
Provides-Extra: r
Provides-Extra: scanpy
Provides-Extra: test
